randomproto.py
randomproto-0.0.1.dist-info/LICENSE
randomproto-0.0.1.dist-info/METADATA
randomproto-0.0.1.dist-info/WHEEL
randomproto-0.0.1.dist-info/top_level.txt
randomproto-0.0.1.dist-info/RECORD
