Metadata-Version: 2.1
Name: randomproto
Version: 0.0.1
Summary: Random protobuf object generator
Home-page: https://github.com/yupingso/randomproto
Author: Yu-Ping Wu
Author-email: yupingso@gmail.com
License: UNKNOWN
Keywords: protobuf proto message random generate generator
Platform: UNKNOWN
Classifier: Programming Language :: Python :: 2.7
Classifier: Programming Language :: Python :: 3.5
Classifier: Programming Language :: Python :: 3.6
Requires-Dist: protobuf (>=3.6.0)
